otailab/__init__.py
otailab/main.py
otailab-0.3.dist-info/METADATA
otailab-0.3.dist-info/WHEEL
otailab-0.3.dist-info/top_level.txt
otailab-0.3.dist-info/RECORD
