Metadata-Version: 2.4
Name: otailab
Version: 0.3
Summary: A Python package for Operations Research and Optimization Algorithms
Home-page: https://github.com/TamilSelvan7708/otailab.git
Author: Tamilselvan A K
Author-email: aktamil13@gmail.com
Classifier: Development Status :: 3 - Alpha
Classifier: Intended Audience :: Science/Research
Classifier: Topic :: Scientific/Engineering
Classifier: Programming Language :: Python :: 3
Classifier: License :: OSI Approved :: MIT License
Classifier: Operating System :: OS Independent
Requires-Python: >=3.6
Requires-Dist: networkx>=2.0
Requires-Dist: matplotlib>=3.0
Requires-Dist: numpy>=1.19.0
Requires-Dist: scipy>=1.6.0
Requires-Dist: sympy>=1.8
Dynamic: author
Dynamic: author-email
Dynamic: classifier
Dynamic: description
Dynamic: description-content-type
Dynamic: home-page
Dynamic: requires-dist
Dynamic: requires-python
Dynamic: summary
